autonomous_agent/__init__.py
autonomous_agent/autonomous_agent.py
autonomous_agent/behaviour.py
autonomous_agent/event.py
autonomous_agent_udit107710-0.0.1.dist-info/METADATA
autonomous_agent_udit107710-0.0.1.dist-info/WHEEL
autonomous_agent_udit107710-0.0.1.dist-info/top_level.txt
autonomous_agent_udit107710-0.0.1.dist-info/RECORD
